range_set.py
range_set-0.3.3.dist-info/LICENSE
range_set-0.3.3.dist-info/LICENSE.APACHE2
range_set-0.3.3.dist-info/LICENSE.MIT
range_set-0.3.3.dist-info/METADATA
range_set-0.3.3.dist-info/WHEEL
range_set-0.3.3.dist-info/top_level.txt
range_set-0.3.3.dist-info/RECORD
