Metadata-Version: 2.1
Name: range_set
Version: 0.3.3
Summary: Efficient storage for sets of mostly-consecutive integers
Home-page: https://github.com/smurfix/range_set
Author: Matthias Urlichs
Author-email: matthias@urlichs.de
License: MIT -or- Apache License 2.0
Keywords: set,coalesce,compact,consecutive
Classifier: License :: OSI Approved :: MIT License
Classifier: License :: OSI Approved :: Apache Software License
Classifier: Programming Language :: Python :: 3 :: Only
Classifier: Programming Language :: Python :: Implementation :: CPython
Classifier: Programming Language :: Python :: Implementation :: PyPy
Classifier: Development Status :: 4 - Beta
Classifier: Intended Audience :: Developers
Classifier: Topic :: Software Development :: Libraries
Requires-Python: >=3.4
License-File: LICENSE
License-File: LICENSE.APACHE2
License-File: LICENSE.MIT
